torchrender3d/__init__.py
torchrender3d/drawing_tools.py
torchrender3d/extract_layer_methods.py
torchrender3d/networkvis3d.py
torchrender3d/parallel_methods.py
torchrender3d-0.0.7.dist-info/LICENSE
torchrender3d-0.0.7.dist-info/METADATA
torchrender3d-0.0.7.dist-info/WHEEL
torchrender3d-0.0.7.dist-info/top_level.txt
torchrender3d-0.0.7.dist-info/RECORD
