Metadata-Version: 2.1
Name: torchrender3d
Version: 0.0.7
Summary: TorchRender3D is an advanced visualization tool designed for PyTorch developers and researchers to explore the internal structure of custom neural networks specifically CNNs. Leveraging the power of VTK (Visualization Toolkit) for 3D rendering, TorchRender3D enables real-time, interactive visualizations of neural network layers and outputs.
Home-page: https://gitlab.com/ml-ppa-derivatives/torchrender3d
Author: Tanumoy Saha
Author-email: sahat@htw-berlin.de
Classifier: Programming Language :: Python :: 3
Classifier: License :: OSI Approved :: Apache Software License
Classifier: Operating System :: Microsoft :: Windows
Classifier: Operating System :: POSIX :: Linux
Classifier: Operating System :: MacOS :: MacOS X
Requires-Python: >=3.10
License-File: LICENSE
Requires-Dist: numpy==2.1.3
Requires-Dist: torch==2.5.1
Requires-Dist: torchvision==0.20.1
Requires-Dist: vtk==9.2.6
Requires-Dist: tqdm==4.66.6
